quetz_frontend/__init__.py
quetz_frontend/_version.py
quetz_frontend/backend.py
quetz_frontend/cli.py
quetz_frontend/paths.py
quetz_frontend/resources.py
quetz_frontend/utils.py
quetz_frontend/app/bootstrap.js
quetz_frontend/app/index.js
quetz_frontend/app/package.json
quetz_frontend/app/publicpath.js
quetz_frontend/app/style.js
quetz_frontend/app/webpack.config.js
quetz_frontend/app/webpack.prod.config.js
quetz_frontend/app/public/site.webmanifest
quetz_frontend/app/public/icons/android-chrome-192x192.png
quetz_frontend/app/public/icons/android-chrome-512x512.png
quetz_frontend/app/public/icons/apple-touch-icon.png
quetz_frontend/app/public/icons/favicon-16x16.png
quetz_frontend/app/public/icons/favicon-32x32.png
quetz_frontend/app/public/icons/favicon.ico
quetz_frontend/app/static/1307.cf16a452f3ce2f777c65.js
quetz_frontend/app/static/170.6d9a218896bc85748da5.js
quetz_frontend/app/static/2106.e83f6e16200a7d1e3846.js
quetz_frontend/app/static/2266.7116801007bb107b9cd2.js
quetz_frontend/app/static/2328.d035e8b88ce4f207a72f.js
quetz_frontend/app/static/2385.c5c8cec1e012ca896b1b.js
quetz_frontend/app/static/2448.ccd77d0747ed683abf49.js
quetz_frontend/app/static/2671.37896a87d25dea91e04a.js
quetz_frontend/app/static/2784.9c883399be92f582f5b0.js
quetz_frontend/app/static/2784.9c883399be92f582f5b0.js.LICENSE.txt
quetz_frontend/app/static/2993.5eca846627dabc01c55b.js
quetz_frontend/app/static/330.758047608fa8b9abf1ac.js
quetz_frontend/app/static/330.758047608fa8b9abf1ac.js.LICENSE.txt
quetz_frontend/app/static/373c04fd2418f5c77eea49d514731058f1907a94ff3b4e5d7c3e5767e8b53d8b.eot
quetz_frontend/app/static/3765.0694e04257d390d269f6.js
quetz_frontend/app/static/3f6d3488cf65374f6f676c315340b0ac2be832bd55240c809448e36ef9b96326.woff
quetz_frontend/app/static/420.d663a215e75f61bebed8.js
quetz_frontend/app/static/4294.8942a2e1aa405902c8df.js
quetz_frontend/app/static/4330.77218072720af112b140.js
quetz_frontend/app/static/4330.77218072720af112b140.js.LICENSE.txt
quetz_frontend-0.4.1.dist-info/LICENSE
quetz_frontend-0.4.1.dist-info/METADATA
quetz_frontend-0.4.1.dist-info/WHEEL
quetz_frontend-0.4.1.dist-info/entry_points.txt
quetz_frontend-0.4.1.dist-info/top_level.txt
quetz_frontend-0.4.1.dist-info/RECORD
