Metadata-Version: 2.1
Name: quetz-frontend
Version: 0.4.1
Summary: Quetz frontend as Quetz server extension
Home-page: https://github.com/mamba-org/quetz-frontend
Author: QuantStack
Keywords: quetz,mamba,conda
Platform: Linux
Platform: Mac OS X
Platform: Windows
Classifier: Intended Audience :: Developers
Classifier: Intended Audience :: System Administrators
Classifier: Intended Audience :: Science/Research
Classifier: License :: OSI Approved :: BSD License
Classifier: Programming Language :: Python
Classifier: Programming Language :: Python :: 3.7
Classifier: Programming Language :: Python :: 3.8
Classifier: Programming Language :: Python :: 3.9
Classifier: Programming Language :: Python :: 3.10
Requires-Python: >=3.7
License-File: LICENSE
Requires-Dist: typer >=0.4.1
Requires-Dist: quetz-server ~=0.4
Provides-Extra: dev
Requires-Dist: black ; extra == 'dev'
Requires-Dist: isort ; extra == 'dev'
Requires-Dist: tbump ; extra == 'dev'
